tests/__init__.py
tests/test_import.py
libiap-0.4.1.dist-info/LICENSE
libiap-0.4.1.dist-info/METADATA
libiap-0.4.1.dist-info/WHEEL
libiap-0.4.1.dist-info/top_level.txt
libiap-0.4.1.dist-info/RECORD
