Metadata-Version: 2.1
Name: libiap
Version: 0.4.1
Summary: Please use https://github.com/umccr-illumina/libica instead
Home-page: https://github.com/umccr-illumina/libiap
Author: UMCCR and Contributors
Author-email: services@umccr.org
License: MIT
Platform: UNKNOWN
Classifier: Development Status :: 7 - Inactive
Requires-Python: >=3.6
Requires-Dist: libica (==0.5.0)
Provides-Extra: dev
Requires-Dist: twine ; extra == 'dev'
Requires-Dist: setuptools ; extra == 'dev'
Requires-Dist: wheel ; extra == 'dev'
